classutilities/__init__.py
classutilities/classproperty.py
classutilities/configclass.py
classutilities/tests/__init__.py
classutilities/tests/test_classproperty.py
classutilities/tests/test_configclass.py
classutilities-0.2.1.dist-info/LICENSE
classutilities-0.2.1.dist-info/METADATA
classutilities-0.2.1.dist-info/WHEEL
classutilities-0.2.1.dist-info/top_level.txt
classutilities-0.2.1.dist-info/RECORD
