Metadata-Version: 2.1
Name: classutilities
Version: 0.2.1
Summary: A simple package that allows having class-level properties and validator for typical configuration classes.
Home-page: https://github.com/david-salac/classutilities
License: UNKNOWN
Platform: UNKNOWN
Classifier: Programming Language :: Python :: 3
Classifier: Operating System :: OS Independent
Requires-Python: >=3.9
License-File: LICENSE
